src/__init__.py
src/core/__init__.py
src/core/ansi.py
src/core/cmd.py
src/core/comp.py
src/core/date.py
src/core/func.py
src/core/hash.py
src/core/iter.py
src/core/logs.py
src/core/op.py
src/core/str.py
src/core/type.py
src/core/var.py
src/mods/http.py
src/mods/json.py
src/mods/path.py
src/mods/re.py
functional_utils-0.0.1.dist-info/LICENSE
functional_utils-0.0.1.dist-info/METADATA
functional_utils-0.0.1.dist-info/WHEEL
functional_utils-0.0.1.dist-info/RECORD
