Metadata-Version: 2.1
Name: functional-utils
Version: 0.0.1
Summary: Functional-based utils for Python following a constructivist approach.
License: MIT
Author: Yuri Ximenes
Author-email: yxm.dev@gmx.ie
Requires-Python: >=3.12,<4.0
Classifier: License :: OSI Approved :: MIT License
Classifier: Programming Language :: Python :: 3
Classifier: Programming Language :: Python :: 3.12
Classifier: Programming Language :: Python :: 3.13
